lightecho_stellar_oracle.py
lightecho_stellar_oracle-2.0.0.dist-info/METADATA
lightecho_stellar_oracle-2.0.0.dist-info/WHEEL
lightecho_stellar_oracle-2.0.0.dist-info/RECORD
