Metadata-Version: 2.1
Name: lightecho_stellar_oracle
Version: 2.0.0
Summary: Python SDK for the Lightecho Stellar Oracle
Home-page: https://github.com/bp-ventures/lightecho-stellar-oracle/tree/trunk/oracle-sdk/python
Author: BP Ventures
Requires-Python: >=3.10,<4.0
Classifier: Programming Language :: Python :: 3
Classifier: Programming Language :: Python :: 3.10
Classifier: Programming Language :: Python :: 3.11
Classifier: Programming Language :: Python :: 3.12
Requires-Dist: stellar-sdk (==11.0.0)
